[
  {
    "title": "大阪大学人間科学研究科にて助教に着任いたしました。",
    "date": "2025-04",
    "content": "この度、大阪大学人間科学研究科にて行動統計科学研究分野の助教に着任いたしました。今後も精進いたします。"
  },
  {
    "title": "博士号を頂きました。",
    "date": "2025-03",
    "content": "この度、東京大学大学院にて博士号をいただきました。今後も精進いたします。"
  },
  {
    "title": "新しいホームページを公開しました。",
    "date": "2024-07",
    "content": "新しいホームページを公開しました。それに伴い、旧ホームぺージは公開を停止しました。"
  },
  {
    "title": "共同研究を開始しました。",
    "date": "2024-06",
    "content": "外部機関との共同研究を開始しました。今後、公開予定です。"
  },
  {
    "title": "論文が採択されました。",
    "date": "2024-05",
    "content": "<i>Journal of Educational and Behavioral Statistics</i>誌に採択された論文がOnlineFirstで公開されました。<a href=\"https://doi.org/10.3102/10769986241245707\">https://doi.org/10.3102/10769986241245707</a>"
  },
  {
    "title": "賞を受賞しました。",
    "date": "2023-11",
    "content": "日本計算機統計学会 第37回シンポジウムにて「一般化多枝選択型認知診断モデルの提案」の題目で学生研究発表賞をいただきました。ありがとうございます。"
  },
  {
    "title": "preprintを公開しました。",
    "date": "2023-07",
    "content": "Open Science Frameworkにて、preprint \"<i>Modeling Partial Knowledge in Multiple-Choice Cognitive Diagnostic Assessment.</i>\" を公開しました。<a href=\"https://doi.org/10.31234/osf.io/wefb7\">https://doi.org/10.31234/osf.io/wefb7</a>"
  }
]

